modelbase2/__init__.py
modelbase2/distributions.py
modelbase2/fit.py
modelbase2/fns.py
modelbase2/label_map.py
modelbase2/linear_label_map.py
modelbase2/mc.py
modelbase2/mca.py
modelbase2/model.py
modelbase2/nnarchitectures.py
modelbase2/npe.py
modelbase2/parallel.py
modelbase2/parameterise.py
modelbase2/paths.py
modelbase2/plot.py
modelbase2/py.typed
modelbase2/scan.py
modelbase2/simulator.py
modelbase2/types.py
modelbase2/experimental/__init__.py
modelbase2/experimental/codegen.py
modelbase2/experimental/diff.py
modelbase2/experimental/notes.md
modelbase2/experimental/source_tools.py
modelbase2/experimental/strikepy.py
modelbase2/experimental/symbolic.py
modelbase2/experimental/tex.py
modelbase2/integrators/__init__.py
modelbase2/integrators/int_assimulo.py
modelbase2/integrators/int_scipy.py
modelbase2/sbml/__init__.py
modelbase2/sbml/_data.py
modelbase2/sbml/_export.py
modelbase2/sbml/_import.py
modelbase2/sbml/_mathml.py
modelbase2/sbml/_name_conversion.py
modelbase2/sbml/_unit_conversion.py
modelbase2/surrogates/__init__.py
modelbase2/surrogates/_poly.py
modelbase2/surrogates/_torch.py
modelbase2-0.7.0.dist-info/METADATA
modelbase2-0.7.0.dist-info/WHEEL
modelbase2-0.7.0.dist-info/licenses/LICENSE
modelbase2-0.7.0.dist-info/RECORD
