Metadata-Version: 2.4
Name: modelbase2
Version: 0.7.0
Summary: A package to build metabolic models
Author-email: Marvin van Aalst <marvin.vanaalst@gmail.com>
Maintainer-email: Marvin van Aalst <marvin.vanaalst@gmail.com>
License-Expression: GPL-3.0-or-later
License-File: LICENSE
Keywords: metabolic,modelling,ode
Classifier: Development Status :: 5 - Production/Stable
Classifier: Environment :: Console
Classifier: Intended Audience :: Developers
Classifier: Intended Audience :: Science/Research
Classifier: License :: OSI Approved :: GNU General Public License v3 or later (GPLv3+)
Classifier: Operating System :: MacOS
Classifier: Operating System :: Microsoft :: Windows
Classifier: Operating System :: OS Independent
Classifier: Operating System :: POSIX
Classifier: Operating System :: Unix
Classifier: Programming Language :: Python :: 3
Classifier: Programming Language :: Python :: 3.11
Classifier: Topic :: Scientific/Engineering
Classifier: Topic :: Software Development
Requires-Python: >=3.12
Requires-Dist: dill>=0.3.9
Requires-Dist: latexify-py>=0.4.4
Requires-Dist: matplotlib>=3.9.2
Requires-Dist: more-itertools>=10.5.0
Requires-Dist: numpy>=2.1.2
Requires-Dist: pandas>=2.2.3
Requires-Dist: parameteriser>=0.1.0
Requires-Dist: pebble>=5.0.7
Requires-Dist: python-libsbml>=5.20.4
Requires-Dist: scipy>=1.14.1
Requires-Dist: seaborn>=0.13.2
Requires-Dist: symbtools>=0.4.0
Requires-Dist: sympy>=1.13.1
Requires-Dist: tabulate>=0.9.0
Requires-Dist: tqdm>=4.66.6
Requires-Dist: typing-extensions>=4.12.2
Provides-Extra: dev
Requires-Dist: coverage>=7.6.4; extra == 'dev'
Requires-Dist: jupyter>=1.1.1; extra == 'dev'
Requires-Dist: mkdocs-jupyter>=0.25.1; extra == 'dev'
Requires-Dist: mkdocs-material>=9.5.42; extra == 'dev'
Requires-Dist: mkdocs>=1.6.1; extra == 'dev'
Requires-Dist: mypy>=1.13.0; extra == 'dev'
Requires-Dist: pre-commit>=4.0.1; extra == 'dev'
Requires-Dist: pyright>=1.1.387; extra == 'dev'
Requires-Dist: pytest-cov>=5.0.0; extra == 'dev'
Requires-Dist: pytest>=8.3.3; extra == 'dev'
Requires-Dist: qtbmodels<0.2,>=0.1.0; extra == 'dev'
Requires-Dist: requests>=2.32.3; extra == 'dev'
Requires-Dist: ruff>=0.7.1; extra == 'dev'
Requires-Dist: ssort>=0.13.0; extra == 'dev'
Requires-Dist: toml-sort<0.24,>=0.23.1; extra == 'dev'
Provides-Extra: torch
Requires-Dist: torch>=2.5.1; extra == 'torch'
